aglink/__init__.py
aglink/__main__.py
aglink/__version__.py
aglink/agl-script.py
aglink/agl.py
aglink/aglink.ini
aglink/cmdw.py
aglink/configset.py
aglink/idm.py
aglink/vping.py
aglink/wget.py
aglink-1.56.data/data/LICENSE.rst
aglink-1.56.data/data/README.rst
aglink-1.56.data/data/__version__.py
aglink-1.56.data/data/aglink.ini
aglink-1.56.dist-info/LICENSE.rst
aglink-1.56.dist-info/METADATA
aglink-1.56.dist-info/WHEEL
aglink-1.56.dist-info/entry_points.txt
aglink-1.56.dist-info/top_level.txt
aglink-1.56.dist-info/RECORD
