Metadata-Version: 2.1
Name: aglink
Version: 1.56
Summary: Generator Links
Home-page: https://bitbucket.org/licface/aglink
Author: Hadi Cahyadi LD
Author-email: cumulus13@gmail.com
Maintainer: cumulus13 Team
Maintainer-email: cumulus13@gmail.com
License: BSD
Project-URL: Documentation, https://bitbucket.org/licface/aglink
Project-URL: Code, https://bitbucket.org/licface/aglink
Platform: UNKNOWN
Classifier: Development Status :: 5 - Production/Stable
Classifier: Intended Audience :: Developers
Classifier: License :: OSI Approved :: BSD License
Classifier: Operating System :: OS Independent
Classifier: Programming Language :: Python
Classifier: Programming Language :: Python :: 2
Classifier: Programming Language :: Python :: 2.7
Requires-Python: >=2.7, !=3.0.*, !=3.1.*, !=3.2.*, !=3.3.*
Requires-Dist: requests
Requires-Dist: cfscrape
Requires-Dist: bs4
Requires-Dist: argparse
Requires-Dist: clipboard
Requires-Dist: idm
Requires-Dist: vping
Requires-Dist: make-colors (>=3.12)
Requires-Dist: make-colors-tc
Requires-Dist: colorama
Requires-Dist: termcolor
Requires-Dist: configset
Requires-Dist: cmdw
Requires-Dist: configparser
Requires-Dist: pywget
Requires-Dist: pydebugger
